LICENSE
MANIFEST.in
README.rst
setup.py
flask_mysso/__init__.py
flask_mysso/annotation.py
flask_mysso/context.py
flask_mysso/errors.py
flask_mysso/jwt.py
flask_mysso/mysso.py
flask_mysso.egg-info/PKG-INFO
flask_mysso.egg-info/SOURCES.txt
flask_mysso.egg-info/dependency_links.txt
flask_mysso.egg-info/not-zip-safe
flask_mysso.egg-info/requires.txt
flask_mysso.egg-info/top_level.txt
requirements/test.txt
tests/__init__.py