Metadata-Version: 2.1
Name: flask-mysso
Version: 0.1
Summary: mysso plugin for Flask
Home-page: UNKNOWN
Author: jadbin
Author-email: jadbin.com@hotmail.com
License: MIT
Platform: UNKNOWN
Classifier: License :: OSI Approved :: MIT License
Classifier: Intended Audience :: Developers
Classifier: Programming Language :: Python
Classifier: Programming Language :: Python :: 3
Classifier: Topic :: Software Development :: Libraries :: Python Modules
Requires-Python: >=3.6
License-File: LICENSE
